verysimplemodule_crisly/__init__.py
verysimplemodule_crisly/add.py
verysimplemodule_crisly/subtract.py
verysimplemodule_crisly/extra/__init__.py
verysimplemodule_crisly/extra/divide.py
verysimplemodule_crisly/extra/multiple.py
verysimplemodule_crisly-0.0.2.dist-info/METADATA
verysimplemodule_crisly-0.0.2.dist-info/WHEEL
verysimplemodule_crisly-0.0.2.dist-info/top_level.txt
verysimplemodule_crisly-0.0.2.dist-info/RECORD
