Metadata-Version: 2.1
Name: verysimplemodule-crisly
Version: 0.0.2
Summary: Pacote de teste
Author: crisly
Author-email: crislymaria21@gmail.com
Keywords: python,primeiro pacote
Classifier: Development Status :: 3 - Alpha
Requires-Dist: numpy
